{
  "type": "Feature",
  "properties": {
    "gn:admin1_code":"83",
    "gn:asciiname":"Ash Shurraf",
    "gn:country_code":"LY",
    "gn:dem":40,
    "gn:feature_class":"P",
    "gn:feature_code":"PPL",
    "gn:name":"Ash Shurraf",
    "gn:population":0,
    "gn:timezone":"Africa/Tripoli",
    "iso:country":"LY",
    "name:und_x_variant":[
        "Esc Scerruf",
        "Ash Shurraf"
    ],
    "wof:name":"Ash Shurraf",
    "wof:placetype":"locality"
},
  "geometry": {"coordinates":[21.51667,29.05],"type":"Point"}
}