{
  "type": "Feature",
  "properties": {
    "gn:admin1_code":"76",
    "gn:asciiname":"Buwayrat al Hasun",
    "gn:country_code":"LY",
    "gn:dem":17,
    "gn:feature_class":"P",
    "gn:feature_code":"PPL",
    "gn:name":"Buwayr\u0101t al \u1e28as\u016bn",
    "gn:population":0,
    "gn:timezone":"Africa/Tripoli",
    "iso:country":"LY",
    "name:ara_x_preferred":[
        "\u0628\u0648\u064a\u0631\u0627\u062a \u0627\u0644\u062d\u0633\u0648\u0646"
    ],
    "name:und_x_variant":[
        "Buwayr\u0101t al \u1e28as\u016bn",
        "Al Bu\u2019ayr\u0101t",
        "Buer\u00e1t el-Hsun",
        "Buer\u00e1t",
        "Buer\u00e0t al-Hsun",
        "Bu\u2019ayr\u0101t al \u1e28as\u016bn",
        "\u0627\u0644\u0628\u0624\u064a\u0631\u0627\u062a",
        "Buwayr\u0101t al \u1e28ass\u016bn"
    ],
    "wof:name":"Buwayrat al Hasun",
    "wof:placetype":"locality"
},
  "geometry": {"coordinates":[15.72576,31.39937],"type":"Point"}
}