{
  "type": "Feature",
  "properties": {
    "gn:admin1_code":"80",
    "gn:asciiname":"Awlad Bu Ra's",
    "gn:country_code":"LY",
    "gn:dem":521,
    "gn:feature_class":"P",
    "gn:feature_code":"PPL",
    "gn:name":"Awl\u0101d B\u016b Ra\u2019s",
    "gn:population":0,
    "gn:timezone":"Africa/Tripoli",
    "iso:country":"LY",
    "name:und_x_variant":[
        "Ul\u00e0d Bu Ras",
        "Awl\u0101d Abu R\u0101s",
        "Awl\u0101d B\u016b Ra\u2019s"
    ],
    "wof:name":"Awlad Bu Ra's",
    "wof:placetype":"locality"
},
  "geometry": {"coordinates":[13.07155,32.1836],"type":"Point"}
}