{
  "type": "Feature",
  "properties": {
    "gn:admin1_code":"74",
    "gn:asciiname":"Tamzin",
    "gn:country_code":"LY",
    "gn:dem":654,
    "gn:feature_class":"P",
    "gn:feature_code":"PPL",
    "gn:name":"\u0162amz\u012bn",
    "gn:population":0,
    "gn:timezone":"Africa/Tripoli",
    "iso:country":"LY",
    "wof:name":"Tamzin",
    "wof:placetype":"locality"
},
  "geometry": {"coordinates":[11.42096,31.85648],"type":"Point"}
}