{
  "type": "Feature",
  "properties": {
    "gn:admin1_code":"80",
    "gn:asciiname":"Qaryat Marwan",
    "gn:country_code":"LY",
    "gn:dem":676,
    "gn:feature_class":"P",
    "gn:feature_code":"PPL",
    "gn:name":"Qaryat Marw\u0101n",
    "gn:population":0,
    "gn:timezone":"Africa/Tripoli",
    "iso:country":"LY",
    "name:und_x_variant":[
        "Meru\u00e1n",
        "Qaryat Murw\u0101n",
        "Marw\u0101n",
        "Qaryat Marw\u0101n"
    ],
    "wof:name":"Qaryat Marwan",
    "wof:placetype":"locality"
},
  "geometry": {"coordinates":[13.06917,32.13861],"type":"Point"}
}