{
  "type": "Feature",
  "properties": {
    "gn:admin1_code":"82",
    "gn:asciiname":"Qabilat Silin",
    "gn:country_code":"LY",
    "gn:dem":98,
    "gn:feature_class":"P",
    "gn:feature_code":"PPL",
    "gn:name":"Qab\u012blat S\u012bl\u012bn",
    "gn:population":0,
    "gn:timezone":"Africa/Tripoli",
    "iso:country":"LY",
    "name:und_x_variant":[
        "S\u012bl\u012bn",
        "Qab\u012blat S\u012bl\u012bn"
    ],
    "wof:name":"Qabilat Silin",
    "wof:placetype":"locality"
},
  "geometry": {"coordinates":[14.17392,32.66826],"type":"Point"}
}