{
  "type": "Feature",
  "properties": {
    "gn:admin1_code":"72",
    "gn:asciiname":"Qaryat ar Rus",
    "gn:country_code":"LY",
    "gn:dem":4,
    "gn:feature_class":"P",
    "gn:feature_code":"PPL",
    "gn:name":"Qaryat ar R\u016b\u015f",
    "gn:population":0,
    "gn:timezone":"Africa/Tripoli",
    "iso:country":"LY",
    "name:und_x_variant":[
        "Qaryat ar Ru\u2019\u016bs",
        "Qaryat ar R\u016b\u015f"
    ],
    "wof:name":"Qaryat ar Rus",
    "wof:placetype":"locality"
},
  "geometry": {"coordinates":[15.1698,32.37389],"type":"Point"}
}