{
  "type": "Feature",
  "properties": {
    "gn:admin1_code":"68",
    "gn:asciiname":"Al Mutrad",
    "gn:country_code":"LY",
    "gn:dem":15,
    "gn:feature_class":"P",
    "gn:feature_code":"PPL",
    "gn:name":"Al Mu\u0163rad",
    "gn:population":0,
    "gn:timezone":"Africa/Tripoli",
    "iso:country":"LY",
    "name:und_x_variant":[
        "Al Mu\u0163\u0163rad",
        "Al Mu\u0163rad"
    ],
    "wof:name":"Al Mutrad",
    "wof:placetype":"locality"
},
  "geometry": {"coordinates":[12.61583,32.76167],"type":"Point"}
}