{
  "type": "Feature",
  "properties": {
    "gn:country":"LY",
    "gn:fcode":"PPL",
    "gn:pop":23164,
    "iso:country":"LY",
    "name:ara_x_preferred":[
        "\u062a\u0648\u0643\u0631\u0629"
    ],
    "name:dut_x_preferred":[
        "Tocra"
    ],
    "name:eng_x_preferred":[
        "Tocra"
    ],
    "name:geo_x_preferred":[
        "\u10e2\u10e3\u10d9\u10e0\u10d0"
    ],
    "name:ger_x_preferred":[
        "Taucheira"
    ],
    "name:gre_x_preferred":[
        "\u03a4\u03b1\u03cd\u03c7\u03b5\u03b9\u03c1\u03b1"
    ],
    "name:ita_x_preferred":[
        "Tocra"
    ],
    "name:spa_x_preferred":[
        "Tocra"
    ],
    "name:swe_x_preferred":[
        "T\u016bkrah"
    ],
    "name:unk_x_variant":[
        "Tokrah"
    ],
    "qs:name":"T\u016bkrah",
    "qs:photos_9r":0,
    "qs:photos_sr":0,
    "qs:pop_sr":"7",
    "wof:name":"T\u016bkrah",
    "wof:placetype":"locality",
    "wof:population":23164
},
  "geometry": {"coordinates":[20.57911,32.53414],"type":"Point"}
}