{
  "type": "Feature",
  "properties": {
    "gn:admin1_code":"72",
    "gn:asciiname":"Qaryat `Ayn Bu al Qa'id",
    "gn:country_code":"LY",
    "gn:dem":4,
    "gn:feature_class":"P",
    "gn:feature_code":"PPL",
    "gn:name":"Qaryat \u2018Ayn B\u016b al Q\u0101\u2019id",
    "gn:population":0,
    "gn:timezone":"Africa/Tripoli",
    "iso:country":"LY",
    "name:und_x_variant":[
        "Qaryat \u2018Ayn bilq\u0101yid",
        "Qaryat \u2018Ayn B\u016b al Q\u0101\u2019id"
    ],
    "wof:name":"Qaryat `Ayn Bu al Qa'id",
    "wof:placetype":"locality"
},
  "geometry": {"coordinates":[15.11542,32.3618],"type":"Point"}
}