{
  "type": "Feature",
  "properties": {
    "gn:admin1_code":"80",
    "gn:asciiname":"Faysalan",
    "gn:country_code":"LY",
    "gn:dem":724,
    "gn:feature_class":"P",
    "gn:feature_code":"PPL",
    "gn:name":"Fay\u015fal\u0101n",
    "gn:population":0,
    "gn:timezone":"Africa/Tripoli",
    "iso:country":"LY",
    "wof:name":"Faysalan",
    "wof:placetype":"locality"
},
  "geometry": {"coordinates":[13.01361,32.095],"type":"Point"}
}