{
  "type": "Feature",
  "properties": {
    "gn:admin1_code":"67",
    "gn:asciiname":"Al Watiyah",
    "gn:country_code":"LY",
    "gn:dem":75,
    "gn:feature_class":"P",
    "gn:feature_code":"PPL",
    "gn:name":"Al W\u0101\u0163\u012byah",
    "gn:population":0,
    "gn:timezone":"Africa/Tripoli",
    "iso:country":"LY",
    "name:und_x_variant":[
        "Al W\u0101\u0163\u012byah",
        "Al Wa\u0163\u012b\u2019ah",
        "Al Wa\u0163yah",
        "\u0627\u0644\u0648\u0627\u0637\u064a\u0629",
        "Al Uotia"
    ],
    "wof:name":"Al Watiyah",
    "wof:placetype":"locality"
},
  "geometry": {"coordinates":[11.7679,32.47636],"type":"Point"}
}