{
  "type": "Feature",
  "properties": {
    "gn:admin1_code":"72",
    "gn:asciiname":"Qarzah",
    "gn:country_code":"LY",
    "gn:dem":176,
    "gn:feature_class":"P",
    "gn:feature_code":"PPL",
    "gn:name":"Qarzah",
    "gn:population":0,
    "gn:timezone":"Africa/Tripoli",
    "iso:country":"LY",
    "name:ara_x_preferred":[
        "\u0642\u0631\u0632\u0629"
    ],
    "name:und_x_variant":[
        "Gh\u00edrza",
        "Qirdah",
        "Qarzah"
    ],
    "wof:name":"Qarzah",
    "wof:placetype":"locality"
},
  "geometry": {"coordinates":[14.5698,30.96592],"type":"Point"}
}