{
  "type": "Feature",
  "properties": {
    "gn:admin1_code":"80",
    "gn:asciiname":"Bu Jabalayn",
    "gn:country_code":"LY",
    "gn:dem":655,
    "gn:feature_class":"P",
    "gn:feature_code":"PPL",
    "gn:name":"B\u016b Jabalayn",
    "gn:population":0,
    "gn:timezone":"Africa/Tripoli",
    "iso:country":"LY",
    "wof:name":"Bu Jabalayn",
    "wof:placetype":"locality"
},
  "geometry": {"coordinates":[12.01825,31.96917],"type":"Point"}
}