{
  "type": "Feature",
  "properties": {
    "gn:admin1_code":"80",
    "gn:asciiname":"Al Mashwashin",
    "gn:country_code":"LY",
    "gn:dem":673,
    "gn:feature_class":"P",
    "gn:feature_code":"PPL",
    "gn:name":"Al Mashwash\u012bn",
    "gn:population":0,
    "gn:timezone":"Africa/Tripoli",
    "iso:country":"LY",
    "name:und_x_variant":[
        "Al Mashwush\u012bn",
        "Al Mashwash\u012bn"
    ],
    "wof:name":"Al Mashwashin",
    "wof:placetype":"locality"
},
  "geometry": {"coordinates":[12.53039,32.06205],"type":"Point"}
}