{
  "type": "Feature",
  "properties": {
    "gn:admin1_code":"82",
    "gn:asciiname":"Al `Amamirah",
    "gn:country_code":"LY",
    "gn:dem":168,
    "gn:feature_class":"P",
    "gn:feature_code":"PPL",
    "gn:name":"Al \u2018Am\u0101mirah",
    "gn:population":0,
    "gn:timezone":"Africa/Tripoli",
    "iso:country":"LY",
    "wof:name":"Al `Amamirah",
    "wof:placetype":"locality"
},
  "geometry": {"coordinates":[14.10694,32.45472],"type":"Point"}
}