{
  "type": "Feature",
  "properties": {
    "gn:admin1_code":"80",
    "gn:asciiname":"Baldat al `Uqaybah",
    "gn:country_code":"LY",
    "gn:dem":706,
    "gn:feature_class":"P",
    "gn:feature_code":"PPL",
    "gn:name":"Baldat al \u2018Uqaybah",
    "gn:population":0,
    "gn:timezone":"Africa/Tripoli",
    "iso:country":"LY",
    "name:und_x_variant":[
        "Al \u2018Uqaybah",
        "Baldat \u2018Uqaybah",
        "El-Agheiba",
        "El-Agh\u00edba",
        "Baldat al \u2018Uqaybah"
    ],
    "wof:name":"Baldat al `Uqaybah",
    "wof:placetype":"locality"
},
  "geometry": {"coordinates":[12.30433,31.99477000000001],"type":"Point"}
}