{
  "type": "Feature",
  "properties": {
    "gn:admin1_code":"56",
    "gn:asciiname":"`Ayn al Ghazaya",
    "gn:country_code":"LY",
    "gn:dem":492,
    "gn:feature_class":"P",
    "gn:feature_code":"PPL",
    "gn:name":"\u2018Ayn al Ghaz\u0101y\u0101",
    "gn:population":0,
    "gn:timezone":"Africa/Tripoli",
    "iso:country":"LY",
    "name:und_x_variant":[
        "Ain Ghezaia",
        "\u2018Ayn Ghaz\u0101yah",
        "\u2018Ayn al Ghaz\u0101y\u0101"
    ],
    "wof:name":"`Ayn al Ghazaya",
    "wof:placetype":"locality"
},
  "geometry": {"coordinates":[10.81064,31.904],"type":"Point"}
}