{
  "type": "Feature",
  "properties": {
    "gn:admin1_code":"74",
    "gn:asciiname":"Tigi",
    "gn:country_code":"LY",
    "gn:dem":188,
    "gn:feature_class":"P",
    "gn:feature_code":"PPL",
    "gn:name":"Tigi",
    "gn:population":0,
    "gn:timezone":"Africa/Tripoli",
    "iso:country":"LY",
    "name:ara_x_preferred":[
        "\u062a\u064a\u062c\u064a"
    ],
    "name:und_x_variant":[
        "Tidji",
        "T\u012bj\u012b"
    ],
    "wof:name":"Tigi",
    "wof:placetype":"locality"
},
  "geometry": {"coordinates":[11.35461,32.01493],"type":"Point"}
}