{
  "type": "Feature",
  "properties": {
    "gn:admin1_code":"80",
    "gn:asciiname":"Al Magharibah",
    "gn:country_code":"LY",
    "gn:dem":843,
    "gn:feature_class":"P",
    "gn:feature_code":"PPL",
    "gn:name":"Al Magh\u0101ribah",
    "gn:population":0,
    "gn:timezone":"Africa/Tripoli",
    "iso:country":"LY",
    "name:und_x_variant":[
        "El-Mug\u0101rba",
        "El-Mag\u00e1rba",
        "Al Magh\u0101ribah"
    ],
    "wof:name":"Al Magharibah",
    "wof:placetype":"locality"
},
  "geometry": {"coordinates":[12.97306,32.08694000000001],"type":"Point"}
}