{
  "type": "Feature",
  "properties": {
    "gn:admin1_code":"56",
    "gn:asciiname":"Baldat Jurayjin",
    "gn:country_code":"LY",
    "gn:dem":644,
    "gn:feature_class":"P",
    "gn:feature_code":"PPL",
    "gn:name":"Baldat Jurayjin",
    "gn:population":0,
    "gn:timezone":"Africa/Tripoli",
    "iso:country":"LY",
    "name:und_x_variant":[
        "Ger\u00edgen",
        "Baldat Jarj\u012bn",
        "Jar\u012bjan",
        "Baldat Jurayjin"
    ],
    "wof:name":"Baldat Jurayjin",
    "wof:placetype":"locality"
},
  "geometry": {"coordinates":[11.60619,31.87991],"type":"Point"}
}