{
  "type": "Feature",
  "properties": {
    "gn:admin1_code":"67",
    "gn:asciiname":"Sidi Bin Zinah",
    "gn:country_code":"LY",
    "gn:dem":8,
    "gn:feature_class":"P",
    "gn:feature_code":"PPL",
    "gn:name":"S\u012bd\u012b Bin Z\u012bnah",
    "gn:population":0,
    "gn:timezone":"Africa/Tripoli",
    "iso:country":"LY",
    "name:ara_x_preferred":[
        "\u0633\u064a\u062f\u064a \u0628\u0646 \u0632\u064a\u0646\u0629"
    ],
    "name:und_x_variant":[
        "Raqd\u0101l\u012bn",
        "Regdalin",
        "S\u012bd\u012b Bin Z\u012bnah",
        "S\u012bd\u012b B\u016b Z\u012bnah",
        "Riqd\u0101l\u012bn"
    ],
    "wof:name":"Sidi Bin Zinah",
    "wof:placetype":"locality"
},
  "geometry": {"coordinates":[11.98729,32.88718],"type":"Point"}
}