{
  "type": "Feature",
  "properties": {
    "gn:admin1_code":"72",
    "gn:asciiname":"Qaryat al Ghawil",
    "gn:country_code":"LY",
    "gn:dem":9,
    "gn:feature_class":"P",
    "gn:feature_code":"PPL",
    "gn:name":"Qaryat al Ghaw\u012bl",
    "gn:population":0,
    "gn:timezone":"Africa/Tripoli",
    "iso:country":"LY",
    "wof:name":"Qaryat al Ghawil",
    "wof:placetype":"locality"
},
  "geometry": {"coordinates":[15.12961,32.37278],"type":"Point"}
}