{
  "type": "Feature",
  "properties": {
    "iso:country":"LY",
    "name:und_x_variant":[
        "Et Tag"
    ],
    "qs:gn_country":"LY",
    "qs:gn_fcode":"PPL",
    "qs:gn_pop":46050,
    "qs:name":"At Taj",
    "qs:name_adm0":"Libya",
    "qs:name_adm1":"\u0627\u0644\u0643\u0641\u0631\u0629",
    "qs:photos":0,
    "qs:photos_1k":0,
    "qs:photos_9k":1,
    "qs:photos_9r":1,
    "qs:photos_all":1,
    "qs:photos_sr":0,
    "qs:placetype":"Town",
    "qs:pop_sr":"7",
    "qs:woe_adm0":23424882,
    "wof:name":"At Taj",
    "wof:placetype":"locality",
    "wof:population":46050
},
  "geometry": {"coordinates":[23.2857,24.20487],"type":"Point"}
}