{
  "type": "Feature",
  "properties": {
    "gn:admin1_code":"73",
    "gn:asciiname":"Waw al Kabir",
    "gn:country_code":"LY",
    "gn:dem":451,
    "gn:feature_class":"P",
    "gn:feature_code":"PPL",
    "gn:name":"W\u0101w al Kab\u012br",
    "gn:population":0,
    "gn:timezone":"Africa/Tripoli",
    "iso:country":"LY",
    "name:und_x_variant":[
        "Uau el Chebir",
        "El Chebir",
        "W\u0101w al Kab\u012br",
        "\u0648\u0627\u0648 \u0627\u0644\u0643\u0628\u064a\u0631"
    ],
    "wof:name":"Waw al Kabir",
    "wof:placetype":"locality"
},
  "geometry": {"coordinates":[16.71528,25.32222],"type":"Point"}
}