{
  "type": "Feature",
  "properties": {
    "gn:admin1_code":"80",
    "gn:asciiname":"Ki`am",
    "gn:country_code":"LY",
    "gn:dem":720,
    "gn:feature_class":"P",
    "gn:feature_code":"PPL",
    "gn:name":"Ki\u2018\u0101m",
    "gn:population":0,
    "gn:timezone":"Africa/Tripoli",
    "iso:country":"LY",
    "name:und_x_variant":[
        "Ka\u2018am",
        "Ki\u2018\u0101m"
    ],
    "wof:name":"Ki`am",
    "wof:placetype":"locality"
},
  "geometry": {"coordinates":[13.00611,32.11028],"type":"Point"}
}