{
  "type": "Feature",
  "properties": {
    "gn:admin1_code":"81",
    "gn:asciiname":"Awlad Abu Salamah",
    "gn:country_code":"LY",
    "gn:dem":584,
    "gn:feature_class":"P",
    "gn:feature_code":"PPL",
    "gn:name":"Awl\u0101d Ab\u016b Sal\u0101mah",
    "gn:population":0,
    "gn:timezone":"Africa/Tripoli",
    "iso:country":"LY",
    "name:und_x_variant":[
        "Awl\u0101d Ab\u016b Sl\u0101mah",
        "Awl\u0101d Ab\u016b Sal\u0101mah"
    ],
    "wof:name":"Awlad Abu Salamah",
    "wof:placetype":"locality"
},
  "geometry": {"coordinates":[13.03333,32.25],"type":"Point"}
}