{
  "type": "Feature",
  "properties": {
    "gn:admin1_code":"72",
    "gn:asciiname":"Qaryat Qararah",
    "gn:country_code":"LY",
    "gn:dem":9,
    "gn:feature_class":"P",
    "gn:feature_code":"PPL",
    "gn:name":"Qaryat Qar\u0101rah",
    "gn:population":0,
    "gn:timezone":"Africa/Tripoli",
    "iso:country":"LY",
    "name:und_x_variant":[
        "Gr\u00e1ra",
        "Qaryat Qar\u0101rah"
    ],
    "wof:name":"Qaryat Qararah",
    "wof:placetype":"locality"
},
  "geometry": {"coordinates":[15.11787,32.38009],"type":"Point"}
}