{
  "type": "Feature",
  "properties": {
    "gn:admin1_code":"79",
    "gn:asciiname":"Nuqtat al Khattabiyah",
    "gn:country_code":"LY",
    "gn:dem":133,
    "gn:feature_class":"P",
    "gn:feature_code":"PPL",
    "gn:name":"Nuq\u0163at al Kha\u0163\u0163\u0101b\u012byah",
    "gn:population":0,
    "gn:timezone":"Africa/Tripoli",
    "iso:country":"LY",
    "wof:name":"Nuqtat al Khattabiyah",
    "wof:placetype":"locality"
},
  "geometry": {"coordinates":[25.0419,31.7705],"type":"Point"}
}