{
  "type": "Feature",
  "properties": {
    "gn:admin1_code":"58",
    "gn:asciiname":"Al Mahjub",
    "gn:cc2":"LY",
    "gn:country_code":"LY",
    "gn:dem":-9999,
    "gn:feature_class":"P",
    "gn:feature_code":"PPL",
    "gn:name":"Al Ma\u1e29j\u016bb",
    "gn:population":0,
    "gn:timezone":"Africa/Tripoli",
    "iso:country":"LY",
    "name:und_x_variant":[
        "Qaryat al Ma\u1e29j\u016bb",
        "Al Ma\u1e29j\u016bb"
    ],
    "wof:name":"Al Mahjub",
    "wof:placetype":"locality"
},
  "geometry": {"coordinates":[14.98333,32.43333],"type":"Point"}
}