{
  "type": "Feature",
  "properties": {
    "gn:admin1_code":"80",
    "gn:asciiname":"Awlad Sa`id",
    "gn:country_code":"LY",
    "gn:dem":706,
    "gn:feature_class":"P",
    "gn:feature_code":"PPL",
    "gn:name":"Awl\u0101d Sa\u2018\u012bd",
    "gn:population":0,
    "gn:timezone":"Africa/Tripoli",
    "iso:country":"LY",
    "name:und_x_variant":[
        "Ulad Said",
        "Awl\u0101d Sa\u2018\u012bd"
    ],
    "wof:name":"Awlad Sa`id",
    "wof:placetype":"locality"
},
  "geometry": {"coordinates":[12.66902,32.08309000000001],"type":"Point"}
}