{
  "type": "Feature",
  "properties": {
    "gn:admin1_code":"80",
    "gn:asciiname":"Qabilat ar Raqa'iqiyah",
    "gn:country_code":"LY",
    "gn:dem":469,
    "gn:feature_class":"P",
    "gn:feature_code":"PPL",
    "gn:name":"Qab\u012blat ar Raq\u0101\u2019iq\u012byah",
    "gn:population":0,
    "gn:timezone":"Africa/Tripoli",
    "iso:country":"LY",
    "wof:name":"Qabilat ar Raqa'iqiyah",
    "wof:placetype":"locality"
},
  "geometry": {"coordinates":[13.20311,31.04337],"type":"Point"}
}