{
  "type": "Feature",
  "properties": {
    "gn:admin1_code":"80",
    "gn:asciiname":"Al Kashalifah",
    "gn:country_code":"LY",
    "gn:dem":681,
    "gn:feature_class":"P",
    "gn:feature_code":"PPL",
    "gn:name":"Al Kash\u0101lifah",
    "gn:population":0,
    "gn:timezone":"Africa/Tripoli",
    "iso:country":"LY",
    "name:und_x_variant":[
        "Al Kash\u0101lifab",
        "Al Kash\u0101lifah"
    ],
    "wof:name":"Al Kashalifah",
    "wof:placetype":"locality"
},
  "geometry": {"coordinates":[13.02583,32.11972],"type":"Point"}
}