{
  "type": "Feature",
  "properties": {
    "gn:admin1_code":"74",
    "gn:asciiname":"Al Hawamid",
    "gn:country_code":"LY",
    "gn:dem":230,
    "gn:feature_class":"P",
    "gn:feature_code":"PPL",
    "gn:name":"Al \u1e28aw\u0101mid",
    "gn:population":0,
    "gn:timezone":"Africa/Tripoli",
    "iso:country":"LY",
    "wof:name":"Al Hawamid",
    "wof:placetype":"locality"
},
  "geometry": {"coordinates":[11.16222,31.97528],"type":"Point"}
}