{
  "type": "Feature",
  "properties": {
    "gn:admin1_code":"77",
    "gn:asciiname":"Qurji",
    "gn:country_code":"LY",
    "gn:dem":12,
    "gn:feature_class":"P",
    "gn:feature_code":"PPL",
    "gn:name":"Qurj\u012b",
    "gn:population":0,
    "gn:timezone":"Africa/Tripoli",
    "iso:country":"LY",
    "name:und_x_variant":[
        "G\u00farghi",
        "Saw\u0101n\u012b Q\u016brj\u012b",
        "Su\u00e1ni G\u00fargi",
        "G\u00fargi",
        "Qurj\u012b"
    ],
    "wof:name":"Qurji",
    "wof:placetype":"locality"
},
  "geometry": {"coordinates":[13.15,32.86667],"type":"Point"}
}