{
  "type": "Feature",
  "properties": {
    "gn:admin1_code":"63",
    "gn:asciiname":"Qaryat al Fa'idiyah",
    "gn:country_code":"LY",
    "gn:dem":770,
    "gn:feature_class":"P",
    "gn:feature_code":"PPL",
    "gn:name":"Qaryat al F\u0101\u2019id\u012byah",
    "gn:population":0,
    "gn:timezone":"Africa/Tripoli",
    "iso:country":"LY",
    "name:ara_x_preferred":[
        "\u0642\u0631\u064a\u0629 \u0627\u0644\u0641\u0627\u0626\u062f\u064a\u0629"
    ],
    "name:und_x_variant":[
        "Z\u00e0uia el-Faid\u00eca",
        "Qaryat al F\u0101\u2019id\u012byah",
        "Al F\u0101yid\u012byah",
        "El-Faid\u00eca",
        "Az Zawiyah al F\u0101\u2019id\u012byah",
        "De Martino",
        "Faidia",
        "El Faldia",
        "Al F\u0101\u2019id\u012byah"
    ],
    "wof:name":"Qaryat al Fa'idiyah",
    "wof:placetype":"locality"
},
  "geometry": {"coordinates":[21.90604,32.68845],"type":"Point"}
}