{
  "type": "Feature",
  "properties": {
    "gn:admin1_code":"82",
    "gn:asciiname":"Qabilat Sidi Mu`ammar",
    "gn:country_code":"LY",
    "gn:dem":328,
    "gn:feature_class":"P",
    "gn:feature_code":"PPL",
    "gn:name":"Qab\u012blat S\u012bd\u012b Mu\u2018ammar",
    "gn:population":0,
    "gn:timezone":"Africa/Tripoli",
    "iso:country":"LY",
    "name:ara_x_preferred":[
        "\u0642\u0628\u064a\u0644\u0629 \u0633\u064a\u062f\u064a \u0645\u0639\u0645\u0631"
    ],
    "name:und_x_variant":[
        "S\u00ecdi Ma\u00e0mmer",
        "S\u012bd\u012b Mu\u2018ammar",
        "Qab\u012blat S\u012bd\u012b Mu\u2018ammar"
    ],
    "wof:name":"Qabilat Sidi Mu`ammar",
    "wof:placetype":"locality"
},
  "geometry": {"coordinates":[13.88036,32.49590999999999],"type":"Point"}
}