{
  "type": "Feature",
  "properties": {
    "gn:admin1_code":"63",
    "gn:asciiname":"As Safsaf",
    "gn:country_code":"LY",
    "gn:dem":649,
    "gn:feature_class":"P",
    "gn:feature_code":"PPL",
    "gn:name":"A\u015f \u015eaf\u015f\u0101f",
    "gn:population":0,
    "gn:timezone":"Africa/Tripoli",
    "iso:country":"LY",
    "name:ara_x_preferred":[
        "\u0627\u0644\u0635\u0641\u0635\u0627\u0641"
    ],
    "name:und_x_variant":[
        "A\u015f \u015eaf\u015faf",
        "A\u015f \u015eaf\u015f\u0101f"
    ],
    "name:urd_x_preferred":[
        "\u0633\u0641\u0635\u0641"
    ],
    "wof:name":"As Safsaf",
    "wof:placetype":"locality"
},
  "geometry": {"coordinates":[21.94976,32.77967],"type":"Point"}
}