{
  "type": "Feature",
  "properties": {
    "gn:admin1_code":"73",
    "gn:asciiname":"Funqul",
    "gn:country_code":"LY",
    "gn:dem":445,
    "gn:feature_class":"P",
    "gn:feature_code":"PPL",
    "gn:name":"Funqul",
    "gn:population":0,
    "gn:timezone":"Africa/Tripoli",
    "iso:country":"LY",
    "name:und_x_variant":[
        "Fongul",
        "Funqul"
    ],
    "wof:name":"Funqul",
    "wof:placetype":"locality"
},
  "geometry": {"coordinates":[14.25,25.96667],"type":"Point"}
}