{
  "type": "Feature",
  "properties": {
    "gn:admin1_code":"69",
    "gn:asciiname":"Hishan `A'ilat Baqi",
    "gn:country_code":"LY",
    "gn:dem":4,
    "gn:feature_class":"P",
    "gn:feature_code":"PPL",
    "gn:name":"\u1e28\u012bsh\u0101n \u2018\u0100\u2019ilat B\u0101q\u012b",
    "gn:population":0,
    "gn:timezone":"Africa/Tripoli",
    "iso:country":"LY",
    "wof:name":"Hishan `A'ilat Baqi",
    "wof:placetype":"locality"
},
  "geometry": {"coordinates":[20.2046,32.26786],"type":"Point"}
}