{
  "type": "Feature",
  "properties": {
    "gn:admin1_code":"80",
    "gn:asciiname":"Ghuram",
    "gn:country_code":"LY",
    "gn:dem":576,
    "gn:feature_class":"P",
    "gn:feature_code":"PPL",
    "gn:name":"Ghur\u0101m",
    "gn:population":0,
    "gn:timezone":"Africa/Tripoli",
    "iso:country":"LY",
    "wof:name":"Ghuram",
    "wof:placetype":"locality"
},
  "geometry": {"coordinates":[12.57311,32.05565],"type":"Point"}
}