{
  "type": "Feature",
  "properties": {
    "gn:admin1_code":"74",
    "gn:asciiname":"Murqus",
    "gn:country_code":"LY",
    "gn:dem":635,
    "gn:feature_class":"P",
    "gn:feature_code":"PPL",
    "gn:name":"Murqu\u015f",
    "gn:population":0,
    "gn:timezone":"Africa/Tripoli",
    "iso:country":"LY",
    "name:ara_x_preferred":[
        "\u0645\u0631\u0642\u0635"
    ],
    "name:und_x_variant":[
        "M\u00e9rghes",
        "Marqu\u015f",
        "Marqas",
        "Murqu\u015f"
    ],
    "wof:name":"Murqus",
    "wof:placetype":"locality"
},
  "geometry": {"coordinates":[11.57047,31.84346],"type":"Point"}
}