{
  "type": "Feature",
  "properties": {
    "gn:admin1_code":"79",
    "gn:asciiname":"Zawiyat Janzur",
    "gn:country_code":"LY",
    "gn:dem":42,
    "gn:feature_class":"P",
    "gn:feature_code":"PPL",
    "gn:name":"Z\u0101wiyat Janz\u016br",
    "gn:population":0,
    "gn:timezone":"Africa/Tripoli",
    "iso:country":"LY",
    "name:ara_x_preferred":[
        "\u0632\u0627\u0648\u064a\u0629 \u062c\u0646\u0632\u0648\u0631"
    ],
    "name:und_x_variant":[
        "Z\u0101wiyat Zanz\u016br",
        "Zeueit D Gianzur",
        "Z\u0101wiyat Janz\u016br"
    ],
    "wof:name":"Zawiyat Janzur",
    "wof:placetype":"locality"
},
  "geometry": {"coordinates":[24.74814,31.97067],"type":"Point"}
}