{
  "type": "Feature",
  "properties": {
    "iso:country":"LY",
    "name:ara_x_colloquial":[
        "Baab Qaraqaarish",
        "Baab Qarqaarish",
        "Bab Qaraqarish",
        "Bab Qarqarish"
    ],
    "name:ara_x_preferred":[
        "B\u00e5b Qarq\u00e5rish"
    ],
    "name:ara_x_variant":[
        "Bab Gargaresh",
        "B\u00e5b Qaraq\u00e5rish",
        "Tarabulus Bab Qarqarish"
    ],
    "name:unk_x_variant":[
        "Tarabulus Bab Qarqarish",
        "B\u00e5b Qarq\u00e5rish"
    ],
    "qs:gn_adm0_cc":"LY",
    "qs:gn_fcode":"PPLX",
    "qs:gn_local":2210247,
    "qs:gn_namadm1":"61",
    "qs:gn_name":"B\u0101b Qarq\u0101rish",
    "qs:local_max":1516,
    "qs:local_sum":2595,
    "qs:localhoods":5,
    "qs:name":"B\u00e5b Qarq\u00e5rish",
    "qs:name_adm0":"Libya",
    "qs:name_adm1":"Tsarrbuus",
    "qs:name_local":"\u0637\u0631\u0627\u0628\u0644\u0633",
    "qs:photo_max":183,
    "qs:photo_sum":857,
    "qs:placetype":"Suburb",
    "qs:quad_count":50,
    "qs:woe_adm0":23424882,
    "qs:woe_adm1":2346144,
    "qs:woe_adm2":0,
    "qs:woe_lau":0,
    "qs:woe_local":1353281,
    "qs:woe_ver":"7.10.0",
    "wof:lang":[
        "ara"
    ],
    "wof:name":"B\u00e5b Qarq\u00e5rish",
    "wof:placetype":"neighbourhood"
},
  "geometry": {"coordinates":[13.160648,32.881086],"type":"Point"}
}