{
  "type": "Feature",
  "properties": {
    "iso:country":"LY",
    "name:ara_x_preferred":[
        "\u0632\u0644\u0637\u0646"
    ],
    "name:arz_x_preferred":[
        "\u0632\u0644\u0637\u0646"
    ],
    "name:ceb_x_preferred":[
        "Zal\u0163an"
    ],
    "name:eng_x_preferred":[
        "Zaltan"
    ],
    "name:fra_x_preferred":[
        "Zenten"
    ],
    "name:fra_x_variant":[
        "Zaltan"
    ],
    "name:nld_x_preferred":[
        "Zaltan"
    ],
    "name:pol_x_preferred":[
        "Zaltan"
    ],
    "name:por_x_preferred":[
        "Zaltan"
    ],
    "name:spa_x_preferred":[
        "Zaltan"
    ],
    "name:swe_x_preferred":[
        "Zal\u0163an"
    ],
    "name:tur_x_preferred":[
        "Zaltan"
    ],
    "name:und_x_variant":[
        "Zelten"
    ],
    "name:zul_x_preferred":[
        "Zaltan"
    ],
    "qs:gn_country":"LY",
    "qs:gn_fcode":"PPL",
    "qs:gn_pop":16291,
    "qs:name":"Zaltan",
    "qs:name_adm0":"Libya",
    "qs:name_adm1":"\u0627\u0644\u0646\u0642\u0627\u0637 \u0627\u0644\u062e\u0645\u0633",
    "qs:photos":0,
    "qs:photos_1k":0,
    "qs:photos_9k":0,
    "qs:photos_9r":0,
    "qs:photos_all":0,
    "qs:photos_sr":0,
    "qs:placetype":"Town",
    "qs:pop_sr":"6",
    "qs:woe_adm0":23424882,
    "wd:wordcount":182,
    "wof:name":"Zaltan",
    "wof:placetype":"locality",
    "wof:population":16291
},
  "geometry": {"coordinates":[11.86647,32.94701],"type":"Point"}
}