{
  "type": "Feature",
  "properties": {
    "gn:admin1_code":"73",
    "gn:asciiname":"`Aqqar",
    "gn:country_code":"LY",
    "gn:dem":487,
    "gn:feature_class":"P",
    "gn:feature_code":"PPL",
    "gn:name":"\u2018Aqq\u0101r",
    "gn:population":0,
    "gn:timezone":"Africa/Tripoli",
    "iso:country":"LY",
    "name:und_x_variant":[
        "Aggar",
        "\u2018Aqq\u0101r"
    ],
    "wof:name":"`Aqqar",
    "wof:placetype":"locality"
},
  "geometry": {"coordinates":[13.53139,25.96333],"type":"Point"}
}