{
  "type": "Feature",
  "properties": {
    "gn:admin1_code":"80",
    "gn:asciiname":"Awlad Khalaf Allah",
    "gn:country_code":"LY",
    "gn:dem":492,
    "gn:feature_class":"P",
    "gn:feature_code":"PPL",
    "gn:name":"Awl\u0101d Khalaf All\u0101h",
    "gn:population":0,
    "gn:timezone":"Africa/Tripoli",
    "iso:country":"LY",
    "name:und_x_variant":[
        "Ul\u00e0d Chalf\u00e0lla",
        "Awl\u0101d Khalaf All\u0101h"
    ],
    "wof:name":"Awlad Khalaf Allah",
    "wof:placetype":"locality"
},
  "geometry": {"coordinates":[12.51773,32.03841],"type":"Point"}
}