{
  "type": "Feature",
  "properties": {
    "gn:admin1_code":"72",
    "gn:asciiname":"Qaryat Abu Sharwal",
    "gn:country_code":"LY",
    "gn:dem":5,
    "gn:feature_class":"P",
    "gn:feature_code":"PPL",
    "gn:name":"Qaryat Ab\u016b Sh\u0101rwal",
    "gn:population":0,
    "gn:timezone":"Africa/Tripoli",
    "iso:country":"LY",
    "wof:name":"Qaryat Abu Sharwal",
    "wof:placetype":"locality"
},
  "geometry": {"coordinates":[15.13265,32.3923],"type":"Point"}
}