{
  "type": "Feature",
  "properties": {
    "gn:admin1_code":"77",
    "gn:asciiname":"Al Hanshir",
    "gn:country_code":"LY",
    "gn:dem":12,
    "gn:feature_class":"P",
    "gn:feature_code":"PPL",
    "gn:name":"Al Hansh\u012br",
    "gn:population":0,
    "gn:timezone":"Africa/Tripoli",
    "iso:country":"LY",
    "name:und_x_variant":[
        "Al Hinsh\u012br",
        "Al Hansh\u012br"
    ],
    "wof:name":"Al Hanshir",
    "wof:placetype":"locality"
},
  "geometry": {"coordinates":[13.23756,32.89762],"type":"Point"}
}