{
  "type": "Feature",
  "properties": {
    "gn:country":"LY",
    "gn:fcode":"PPL",
    "gn:population":15543,
    "iso:country":"LY",
    "name:ara_x_preferred":[
        "\u0633\u0644\u0648\u0642"
    ],
    "name:azb_x_preferred":[
        "\u0633\u0644\u0648\u0642"
    ],
    "name:eng_x_preferred":[
        "Suluq"
    ],
    "name:fas_x_preferred":[
        "\u0633\u0644\u0648\u0642"
    ],
    "name:ind_x_preferred":[
        "Suluq"
    ],
    "name:ita_x_preferred":[
        "Soluch"
    ],
    "name:jpn_x_preferred":[
        "\u30bd\u30eb\u30c1"
    ],
    "name:kat_x_preferred":[
        "\u10e1\u10d4\u10da\u10e3\u10e5\u10d8"
    ],
    "name:nld_x_preferred":[
        "Suluq"
    ],
    "name:pol_x_preferred":[
        "Suluk"
    ],
    "name:und_x_variant":[
        "Qaryat Sal\u016bq"
    ],
    "qs_pg:aaroncc":"LY",
    "qs_pg:gn_country":"LY",
    "qs_pg:gn_fcode":"PPL",
    "qs_pg:gn_pop":15543,
    "qs_pg:name":"Sul\u016bq",
    "qs_pg:photos_9r":0,
    "qs_pg:photos_sr":0,
    "qs_pg:pop_sr":6,
    "qs_pg:qs_pg_placetype":"locality",
    "wof:name":"Sul\u016bq",
    "wof:placetype":"locality",
    "wof:population":15543
},
  "geometry": {"coordinates":[20.25205,31.66818],"type":"Point"}
}