{
  "type": "Feature",
  "properties": {
    "gn:admin1_code":"65",
    "gn:asciiname":"Al Hawwari",
    "gn:country_code":"LY",
    "gn:dem":382,
    "gn:feature_class":"P",
    "gn:feature_code":"PPL",
    "gn:name":"Al Haww\u0101r\u012b",
    "gn:population":0,
    "gn:timezone":"Africa/Tripoli",
    "iso:country":"LY",
    "wof:name":"Al Hawwari",
    "wof:placetype":"locality"
},
  "geometry": {"coordinates":[23.16667,24.31667],"type":"Point"}
}