{
  "type": "Feature",
  "properties": {
    "gn:admin1_code":"80",
    "gn:asciiname":"Baldat al Kurumah",
    "gn:country_code":"LY",
    "gn:dem":633,
    "gn:feature_class":"P",
    "gn:feature_code":"PPL",
    "gn:name":"Baldat al Kur\u016bmah",
    "gn:population":0,
    "gn:timezone":"Africa/Tripoli",
    "iso:country":"LY",
    "name:und_x_variant":[
        "El-Cr\u00f3ma",
        "Al Kur\u016bmah",
        "Baldat al Kur\u016bmah"
    ],
    "wof:name":"Baldat al Kurumah",
    "wof:placetype":"locality"
},
  "geometry": {"coordinates":[11.88729,31.86348],"type":"Point"}
}