{
  "type": "Feature",
  "properties": {
    "gn:admin1_code":"74",
    "gn:asciiname":"Wazin",
    "gn:country_code":"LY",
    "gn:dem":419,
    "gn:feature_class":"P",
    "gn:feature_code":"PPL",
    "gn:name":"W\u0101zin",
    "gn:population":0,
    "gn:timezone":"Africa/Tripoli",
    "iso:country":"LY",
    "name:ara_x_preferred":[
        "W\u0101zin"
    ],
    "name:ara_x_variant":[
        "\u0648\u0627\u0632\u0646"
    ],
    "name:und_x_variant":[
        "Uazzen",
        "Wazz\u0101n",
        "W\u0101zin"
    ],
    "wof:name":"Wazin",
    "wof:placetype":"locality"
},
  "geometry": {"coordinates":[10.66532,31.942],"type":"Point"}
}