{
  "type": "Feature",
  "properties": {
    "gn:admin1_code":"74",
    "gn:asciiname":"Buqayqilah",
    "gn:country_code":"LY",
    "gn:dem":631,
    "gn:feature_class":"P",
    "gn:feature_code":"PPL",
    "gn:name":"Buqayq\u012blah",
    "gn:population":0,
    "gn:timezone":"Africa/Tripoli",
    "iso:country":"LY",
    "name:und_x_variant":[
        "Bghighila",
        "Buqayq\u012blah"
    ],
    "wof:name":"Buqayqilah",
    "wof:placetype":"locality"
},
  "geometry": {"coordinates":[11.58398,31.86168],"type":"Point"}
}