{
  "type": "Feature",
  "properties": {
    "iso:country":"LY",
    "qs:gn_pop":0,
    "qs:name":"Sardalas",
    "qs:name_adm0":"Libya",
    "qs:name_adm1":"\u0623\u0648\u0628\u0627\u0631\u064a",
    "qs:photos":24,
    "qs:photos_1k":5,
    "qs:photos_9k":1,
    "qs:photos_9r":1,
    "qs:photos_all":24,
    "qs:photos_sr":1,
    "qs:placetype":"Town",
    "qs:pop_sr":"0",
    "qs:woe_adm0":23424882,
    "wof:name":"Sardalas",
    "wof:placetype":"locality"
},
  "geometry": {"coordinates":[10.560497,25.781601],"type":"Point"}
}