{
  "type": "Feature",
  "properties": {
    "gn:admin1_code":"82",
    "gn:asciiname":"Na`imah",
    "gn:country_code":"LY",
    "gn:dem":25,
    "gn:feature_class":"P",
    "gn:feature_code":"PPL",
    "gn:name":"Na\u2018\u012bmah",
    "gn:population":0,
    "gn:timezone":"Africa/Tripoli",
    "iso:country":"LY",
    "name:und_x_variant":[
        "Naima",
        "Na\u2018\u012bmah",
        "\u0646\u0639\u064a\u0645\u0629"
    ],
    "wof:name":"Na`imah",
    "wof:placetype":"locality"
},
  "geometry": {"coordinates":[14.66886,32.43162],"type":"Point"}
}