{
  "type": "Feature",
  "properties": {
    "iso:country":"LY",
    "name:ara_x_colloquial":[
        "Al Urubah",
        "Al \u2018Urubah"
    ],
    "name:ara_x_preferred":[
        "Al \u2018Ur\u016bbah",
        "\u0642\u0646\u0627\u0629 \u0627\u0644\u0631\u0623\u064a"
    ],
    "name:eng_x_preferred":[
        "Al Urubah"
    ],
    "qs:gn_adm0_cc":"LY",
    "qs:gn_fcode":"PPLX",
    "qs:gn_local":88319,
    "qs:gn_nam_loc":"Banghazi, \u0628\u0646\u063a\u0627\u0632\u064a, LY",
    "qs:gn_namadm1":"54",
    "qs:gn_name":"Al \u2018Ur\u016bbah",
    "qs:local_max":237,
    "qs:local_sum":255,
    "qs:localhoods":2,
    "qs:name":"Al \u2018Ur\u016bbah",
    "qs:name_adm0":"Libya",
    "qs:name_adm1":"Banghazi",
    "qs:name_local":"\u0628\u0646\u063a\u0627\u0632\u064a",
    "qs:photo_max":35,
    "qs:photo_sum":237,
    "qs:placetype":"Suburb",
    "qs:quad_count":22,
    "qs:woe_adm0":23424882,
    "qs:woe_adm1":2346137,
    "qs:woe_adm2":0,
    "qs:woe_lau":0,
    "qs:woe_local":1352831,
    "qs:woe_ver":"7.10.0",
    "wd:wordcount":141,
    "wof:lang":[
        "ara"
    ],
    "wof:name":"Al \u2018Ur\u016bbah",
    "wof:placetype":"neighbourhood"
},
  "geometry": {"coordinates":[20.064871,32.118682],"type":"Point"}
}