{
  "type": "Feature",
  "properties": {
    "gn:admin1_code":"80",
    "gn:asciiname":"Al `Ubayyat",
    "gn:country_code":"LY",
    "gn:dem":707,
    "gn:feature_class":"P",
    "gn:feature_code":"PPL",
    "gn:name":"Al \u2018Ubayy\u0101t",
    "gn:population":0,
    "gn:timezone":"Africa/Tripoli",
    "iso:country":"LY",
    "wof:name":"Al `Ubayyat",
    "wof:placetype":"locality"
},
  "geometry": {"coordinates":[12.69528,32.08306],"type":"Point"}
}