{
  "type": "Feature",
  "properties": {
    "gn:admin1_code":"63",
    "gn:asciiname":"Kuhuf Tuhudiyah",
    "gn:country_code":"LY",
    "gn:dem":696,
    "gn:feature_class":"P",
    "gn:feature_code":"PPL",
    "gn:name":"Kuh\u016bf Tu\u1e29\u016bd\u012byah",
    "gn:population":0,
    "gn:timezone":"Africa/Tripoli",
    "iso:country":"LY",
    "name:und_x_variant":[
        "Ghaw\u0163 wa Kuh\u016bf Tu\u1e29\u016bd\u012byah",
        "Kuh\u016bf Tu\u1e29\u016bd\u012byah"
    ],
    "wof:name":"Kuhuf Tuhudiyah",
    "wof:placetype":"locality"
},
  "geometry": {"coordinates":[21.87127000000001,32.71614],"type":"Point"}
}