{
  "type": "Feature",
  "properties": {
    "gn:admin1_code":"72",
    "gn:asciiname":"Qaryat at Tawalikiyah",
    "gn:country_code":"LY",
    "gn:dem":10,
    "gn:feature_class":"P",
    "gn:feature_code":"PPL",
    "gn:name":"Qaryat at Taw\u0101lik\u012byah",
    "gn:population":0,
    "gn:timezone":"Africa/Tripoli",
    "iso:country":"LY",
    "wof:name":"Qaryat at Tawalikiyah",
    "wof:placetype":"locality"
},
  "geometry": {"coordinates":[15.11889,32.39181],"type":"Point"}
}