{
  "type": "Feature",
  "properties": {
    "gn:admin1_code":"80",
    "gn:asciiname":"Sadrus",
    "gn:country_code":"LY",
    "gn:dem":558,
    "gn:feature_class":"P",
    "gn:feature_code":"PPL",
    "gn:name":"Sadr\u016bs",
    "gn:population":0,
    "gn:timezone":"Africa/Tripoli",
    "iso:country":"LY",
    "name:und_x_variant":[
        "Sedr\u00f9res",
        "Sadr\u016bs"
    ],
    "wof:name":"Sadrus",
    "wof:placetype":"locality"
},
  "geometry": {"coordinates":[13.09944,32.18444],"type":"Point"}
}