{
  "type": "Feature",
  "properties": {
    "gn:country":"LY",
    "gn:fcode":"PPL",
    "gn:population":46350,
    "iso:country":"LY",
    "name:ara_x_preferred":[
        "Qa\u015fr Ban\u012b Wal\u012bd"
    ],
    "name:ara_x_variant":[
        "Ban\u012b Wal\u012bd",
        "\u0642\u0635\u0631 \u0628\u0646\u064a \u0648\u0644\u064a\u062f",
        "\u0628\u0646\u064a \u0648\u0644\u064a\u062f"
    ],
    "name:bel_x_preferred":[
        "\u0413\u043e\u0440\u0430\u0434 \u0411\u0435\u043d\u0456-\u0412\u0430\u043b\u0456\u0434"
    ],
    "name:bul_x_preferred":[
        "\u0411\u0430\u043d\u0438 \u0423\u0430\u043b\u0438\u0434"
    ],
    "name:ces_x_preferred":[
        "Ban\u00ed Wal\u00edd"
    ],
    "name:eng_x_preferred":[
        "Bani Walid"
    ],
    "name:epo_x_preferred":[
        "Beni Valid"
    ],
    "name:fas_x_preferred":[
        "\u0628\u0646\u06cc\u200c\u0648\u0644\u06cc\u062f"
    ],
    "name:fra_x_preferred":[
        "Beni Ulid"
    ],
    "name:hbs_x_preferred":[
        "Bani Valid"
    ],
    "name:hun_x_preferred":[
        "Bani Val\u00edd"
    ],
    "name:ind_x_preferred":[
        "Beni Ulid"
    ],
    "name:jpn_x_preferred":[
        "\u30d0\u30cb\u30ef\u30ea\u30fc\u30c9"
    ],
    "name:kat_x_preferred":[
        "\u10d1\u10d0\u10dc\u10d8-\u10d5\u10d0\u10da\u10d8\u10d3\u10d8"
    ],
    "name:kor_x_preferred":[
        "\ubc14\ub2c8\uc648\ub9ac\ub4dc"
    ],
    "name:lit_x_preferred":[
        "Bani Validas"
    ],
    "name:rus_x_preferred":[
        "\u0411\u0435\u043d\u0438-\u0412\u0430\u043b\u0438\u0434"
    ],
    "name:scn_x_preferred":[
        "Beni Ulid"
    ],
    "name:srp_x_preferred":[
        "\u0411\u0430\u043d\u0438 \u0412\u0430\u043b\u0438\u0434"
    ],
    "name:ukr_x_preferred":[
        "\u0411\u0435\u043d\u0456-\u0412\u0430\u043b\u0456\u0434"
    ],
    "name:und_x_variant":[
        "Gasr B\u00e9ni Ul\u00edd"
    ],
    "name:urd_x_preferred":[
        "\u0628\u0646\u06cc \u0648\u0644\u06cc\u062f"
    ],
    "name:vol_x_preferred":[
        "B\u00e4ni V\u00e4lid"
    ],
    "name:zho_x_preferred":[
        "\u62dc\u5c3c\u6c83\u5229\u5fb7"
    ],
    "qs_pg:aaroncc":"LY",
    "qs_pg:gn_country":"LY",
    "qs_pg:gn_fcode":"PPL",
    "qs_pg:gn_pop":46350,
    "qs_pg:name":"Ban\u012b Wal\u012bd",
    "qs_pg:photos_9r":0,
    "qs_pg:photos_sr":0,
    "qs_pg:pop_sr":8,
    "qs_pg:qs_pg_placetype":"locality",
    "wof:name":"Ban\u012b Wal\u012bd",
    "wof:placetype":"locality",
    "wof:population":46350
},
  "geometry": {"coordinates":[13.99422,31.75662],"type":"Point"}
}