{
  "type": "Feature",
  "properties": {
    "gn:admin1_code":"69",
    "gn:asciiname":"At Taribjah",
    "gn:country_code":"LY",
    "gn:dem":9,
    "gn:feature_class":"P",
    "gn:feature_code":"PPL",
    "gn:name":"At Taribjah",
    "gn:population":0,
    "gn:timezone":"Africa/Tripoli",
    "iso:country":"LY",
    "name:und_x_variant":[
        "Qaryat a\u0163 \u0162aribjah",
        "At Taribjah"
    ],
    "wof:name":"At Taribjah",
    "wof:placetype":"locality"
},
  "geometry": {"coordinates":[19.94959,31.87383],"type":"Point"}
}