{
  "type": "Feature",
  "properties": {
    "gn:admin1_code":"76",
    "gn:asciiname":"An Nawfaliyah",
    "gn:country_code":"LY",
    "gn:dem":52,
    "gn:feature_class":"P",
    "gn:feature_code":"PPL",
    "gn:name":"An Nawfal\u012byah",
    "gn:population":0,
    "gn:timezone":"Africa/Tripoli",
    "iso:country":"LY",
    "name:und_x_variant":[
        "Nofil\u00eda",
        "Zauiet en-Nofilia",
        "Nufilia",
        "En-Nofil\u00eda",
        "Zauia-en-Nofilia",
        "An N\u016bfal\u012byah",
        "An Nawfal\u012byah",
        "\u0627\u0644\u0646\u0648\u0641\u0644\u064a\u0629",
        "El Noflia"
    ],
    "wof:name":"An Nawfaliyah",
    "wof:placetype":"locality"
},
  "geometry": {"coordinates":[17.83544,30.77784],"type":"Point"}
}