{
  "type": "Feature",
  "properties": {
    "gn:admin1_code":"76",
    "gn:asciiname":"An Nawfaliyah",
    "gn:country_code":"LY",
    "gn:dem":52,
    "gn:feature_class":"P",
    "gn:feature_code":"PPL",
    "gn:name":"An Nawfal\u012byah",
    "gn:population":0,
    "gn:timezone":"Africa/Tripoli",
    "iso:country":"LY",
    "name:ara_x_preferred":[
        "\u0627\u0644\u0646\u0648\u0641\u0644\u064a\u0629"
    ],
    "name:deu_x_preferred":[
        "An-Nufalija"
    ],
    "name:epo_x_preferred":[
        "Nufalija"
    ],
    "name:fra_x_preferred":[
        "Nofilia"
    ],
    "name:kat_x_preferred":[
        "\u10d0\u10dc-\u10dc\u10dd\u10e4\u10d0\u10da\u10d8\u10d0"
    ],
    "name:pol_x_preferred":[
        "An-Naufalijja"
    ],
    "name:por_x_preferred":[
        "Nofalia"
    ],
    "name:rus_x_preferred":[
        "\u041d\u043e\u0444\u0430\u043b\u0438\u044f"
    ],
    "name:sco_x_preferred":[
        "An Nawfaliyah"
    ],
    "name:spa_x_preferred":[
        "Naufaliya"
    ],
    "name:und_x_variant":[
        "Nofil\u00eda",
        "Zauiet en-Nofilia",
        "Nufilia",
        "En-Nofil\u00eda",
        "Zauia-en-Nofilia",
        "An N\u016bfal\u012byah",
        "An Nawfal\u012byah",
        "\u0627\u0644\u0646\u0648\u0641\u0644\u064a\u0629",
        "El Noflia"
    ],
    "wof:name":"An Nawfaliyah",
    "wof:placetype":"locality"
},
  "geometry": {"coordinates":[17.83544,30.77784],"type":"Point"}
}