{
  "type": "Feature",
  "properties": {
    "gn:admin1_code":"80",
    "gn:asciiname":"Bani Wazir",
    "gn:country_code":"LY",
    "gn:dem":800,
    "gn:feature_class":"P",
    "gn:feature_code":"PPL",
    "gn:name":"Ban\u012b Waz\u012br",
    "gn:population":0,
    "gn:timezone":"Africa/Tripoli",
    "iso:country":"LY",
    "name:und_x_variant":[
        "Beni Uzir",
        "Ban\u012b Waz\u012br"
    ],
    "wof:name":"Bani Wazir",
    "wof:placetype":"locality"
},
  "geometry": {"coordinates":[12.98472,32.08583],"type":"Point"}
}