{
  "type": "Feature",
  "properties": {
    "gn:admin1_code":"80",
    "gn:asciiname":"Awlad `Ali",
    "gn:country_code":"LY",
    "gn:dem":743,
    "gn:feature_class":"P",
    "gn:feature_code":"PPL",
    "gn:name":"Awl\u0101d \u2018Al\u012b",
    "gn:population":0,
    "gn:timezone":"Africa/Tripoli",
    "iso:country":"LY",
    "name:und_x_variant":[
        "Ulad Al\u00ed",
        "Baldat Awl\u0101d \u2018Al\u012b",
        "Awl\u0101d \u2018Al\u012b"
    ],
    "wof:name":"Awlad `Ali",
    "wof:placetype":"locality"
},
  "geometry": {"coordinates":[12.37154,32.01579],"type":"Point"}
}