{
  "type": "Feature",
  "properties": {
    "iso:country":"LY",
    "qs:gn_pop":0,
    "qs:name":"\u0627\u0644\u0628\u064a\u0636\u0627",
    "qs:name_adm0":"Libya",
    "qs:name_adm1":"\u0627\u0644\u062c\u0628\u0644 \u0627\u0644\u0627\u062e\u0636\u0631",
    "qs:photos":93,
    "qs:photos_1k":19,
    "qs:photos_9k":1,
    "qs:photos_9r":3,
    "qs:photos_all":93,
    "qs:photos_sr":3,
    "qs:placetype":"Town",
    "qs:pop_sr":"0",
    "qs:woe_adm0":23424882,
    "wof:name":"\u0627\u0644\u0628\u064a\u0636\u0627",
    "wof:placetype":"locality"
},
  "geometry": {"coordinates":[21.855754,32.822912],"type":"Point"}
}