{
  "type": "Feature",
  "properties": {
    "gn:admin1_code":"66",
    "gn:asciiname":"Al Masil",
    "gn:country_code":"LY",
    "gn:dem":647,
    "gn:feature_class":"P",
    "gn:feature_code":"PPL",
    "gn:name":"Al Mas\u012bl",
    "gn:population":0,
    "gn:timezone":"Africa/Tripoli",
    "iso:country":"LY",
    "wof:name":"Al Masil",
    "wof:placetype":"locality"
},
  "geometry": {"coordinates":[20.96667,32.26667],"type":"Point"}
}