{
  "type": "Feature",
  "properties": {
    "gn:admin1_code":"80",
    "gn:asciiname":"Awlad Yusuf",
    "gn:country_code":"LY",
    "gn:dem":722,
    "gn:feature_class":"P",
    "gn:feature_code":"PPL",
    "gn:name":"Awl\u0101d Y\u016bsuf",
    "gn:population":0,
    "gn:timezone":"Africa/Tripoli",
    "iso:country":"LY",
    "name:und_x_variant":[
        "Ul\u00e0d I\u00fasef",
        "Awl\u0101d Y\u016bsuf"
    ],
    "wof:name":"Awlad Yusuf",
    "wof:placetype":"locality"
},
  "geometry": {"coordinates":[12.68194,32.07056],"type":"Point"}
}