{
  "type": "Feature",
  "properties": {
    "gn:admin1_code":"77",
    "gn:asciiname":"As Sawa`idiyah",
    "gn:country_code":"LY",
    "gn:dem":603,
    "gn:feature_class":"P",
    "gn:feature_code":"PPL",
    "gn:name":"As Saw\u0101\u2018id\u012byah",
    "gn:population":0,
    "gn:timezone":"Africa/Tripoli",
    "iso:country":"LY",
    "name:und_x_variant":[
        "Al Wa\u2018d\u012byah",
        "Es-Suaad\u00eca",
        "Es-Suad\u00eda",
        "As Saw\u0101\u2018id\u012byah"
    ],
    "wof:name":"As Sawa`idiyah",
    "wof:placetype":"locality"
},
  "geometry": {"coordinates":[13.08278,32.22028],"type":"Point"}
}