{
  "type": "Feature",
  "properties": {
    "gn:admin1_code":"80",
    "gn:asciiname":"Mazuzah",
    "gn:country_code":"LY",
    "gn:dem":514,
    "gn:feature_class":"P",
    "gn:feature_code":"PPL",
    "gn:name":"M\u0101z\u016bzah",
    "gn:population":0,
    "gn:timezone":"Africa/Tripoli",
    "iso:country":"LY",
    "wof:name":"Mazuzah",
    "wof:placetype":"locality"
},
  "geometry": {"coordinates":[13.05,31.26667],"type":"Point"}
}