{
  "type": "Feature",
  "properties": {
    "gn:admin1_code":"70",
    "gn:asciiname":"Zawiyat Bisharah",
    "gn:country_code":"LY",
    "gn:dem":632,
    "gn:feature_class":"P",
    "gn:feature_code":"PPL",
    "gn:name":"Z\u0101wiyat Bish\u0101rah",
    "gn:population":0,
    "gn:timezone":"Africa/Tripoli",
    "iso:country":"LY",
    "name:ara_x_preferred":[
        "\u0632\u0627\u0648\u064a\u0629 \u0628\u0634\u0627\u0631\u0629"
    ],
    "name:und_x_variant":[
        "Zauiet Bsci\u00e1r",
        "Z\u0101wiyat Bish\u0101rah"
    ],
    "wof:name":"Zawiyat Bisharah",
    "wof:placetype":"locality"
},
  "geometry": {"coordinates":[22.22032,32.76695],"type":"Point"}
}