{
  "type": "Feature",
  "properties": {
    "gn:admin1_code":"63",
    "gn:asciiname":"Qasr Libiya",
    "gn:country_code":"LY",
    "gn:dem":436,
    "gn:feature_class":"P",
    "gn:feature_code":"PPL",
    "gn:name":"Qa\u015fr L\u012bbiy\u0101",
    "gn:population":0,
    "gn:timezone":"Africa/Tripoli",
    "iso:country":"LY",
    "wof:name":"Qasr Libiya",
    "wof:placetype":"locality"
},
  "geometry": {"coordinates":[21.41667,32.63333],"type":"Point"}
}