{
  "type": "Feature",
  "properties": {
    "gn:admin1_code":"74",
    "gn:asciiname":"Az Zaram",
    "gn:country_code":"LY",
    "gn:dem":273,
    "gn:feature_class":"P",
    "gn:feature_code":"PPL",
    "gn:name":"Az Zaram",
    "gn:population":0,
    "gn:timezone":"Africa/Tripoli",
    "iso:country":"LY",
    "name:ara_x_preferred":[
        "\u0627\u0644\u0632\u0631\u0645"
    ],
    "name:und_x_variant":[
        "Algahazaya",
        "Al Ghazz\u0101b\u012byah",
        "Az Zaram"
    ],
    "wof:name":"Az Zaram",
    "wof:placetype":"locality"
},
  "geometry": {"coordinates":[10.83529,32.002],"type":"Point"}
}