{
  "type": "Feature",
  "properties": {
    "gn:admin1_code":"80",
    "gn:asciiname":"Al Qusayr",
    "gn:country_code":"LY",
    "gn:dem":754,
    "gn:feature_class":"P",
    "gn:feature_code":"PPL",
    "gn:name":"Al Qu\u015fayr",
    "gn:population":0,
    "gn:timezone":"Africa/Tripoli",
    "iso:country":"LY",
    "wof:name":"Al Qusayr",
    "wof:placetype":"locality"
},
  "geometry": {"coordinates":[12.54765,32.07153],"type":"Point"}
}