{
  "type": "Feature",
  "properties": {
    "gn:admin1_code":"77",
    "gn:asciiname":"Funduq al `Allus",
    "gn:country_code":"LY",
    "gn:dem":69,
    "gn:feature_class":"P",
    "gn:feature_code":"PPL",
    "gn:name":"Funduq al \u2018All\u016b\u015f",
    "gn:population":0,
    "gn:timezone":"Africa/Tripoli",
    "iso:country":"LY",
    "name:ara_x_preferred":[
        "\u0641\u0646\u062f\u0642 \u0627\u0644\u0639\u0644\u0648\u0635"
    ],
    "name:und_x_variant":[
        "Fundug al \u2018All\u016b\u015f",
        "F\u00f3ndugh el-All\u00fas",
        "Funduq al \u2018All\u016b\u015f"
    ],
    "wof:name":"Funduq al `Allus",
    "wof:placetype":"locality"
},
  "geometry": {"coordinates":[13.94002,32.7094],"type":"Point"}
}