{
  "type": "Feature",
  "properties": {
    "gn:admin1_code":"80",
    "gn:asciiname":"Qaryat Jital",
    "gn:country_code":"LY",
    "gn:dem":663,
    "gn:feature_class":"P",
    "gn:feature_code":"PPL",
    "gn:name":"Qaryat J\u012bt\u0101l",
    "gn:population":0,
    "gn:timezone":"Africa/Tripoli",
    "iso:country":"LY",
    "name:ara_x_preferred":[
        "\u0642\u0631\u064a\u0629 \u062c\u064a\u0637\u0627\u0644"
    ],
    "name:ara_x_variant":[
        "\u0642\u0631\u064a\u0629 \u062c\u064a\u062a\u0627\u0644"
    ],
    "name:und_x_variant":[
        "Geit\u00e1l",
        "Qaryat J\u012b\u0163\u0101l",
        "Jay\u0163\u0101l",
        "Qaryat J\u012bt\u0101l"
    ],
    "wof:name":"Qaryat Jital",
    "wof:placetype":"locality"
},
  "geometry": {"coordinates":[11.88153,31.8967],"type":"Point"}
}