{
  "type": "Feature",
  "properties": {
    "gn:admin1_code":"81",
    "gn:asciiname":"As Sawani",
    "gn:country_code":"LY",
    "gn:dem":60,
    "gn:feature_class":"P",
    "gn:feature_code":"PPL",
    "gn:name":"As Saw\u0101n\u012b",
    "gn:population":0,
    "gn:timezone":"Africa/Tripoli",
    "iso:country":"LY",
    "wof:name":"As Sawani",
    "wof:placetype":"locality"
},
  "geometry": {"coordinates":[13.06667,32.71667],"type":"Point"}
}