{
  "type": "Feature",
  "properties": {
    "gn:admin1_code":"80",
    "gn:asciiname":"Awlad Khalifah",
    "gn:country_code":"LY",
    "gn:dem":663,
    "gn:feature_class":"P",
    "gn:feature_code":"PPL",
    "gn:name":"Awl\u0101d Khal\u012bfah",
    "gn:population":0,
    "gn:timezone":"Africa/Tripoli",
    "iso:country":"LY",
    "name:und_x_variant":[
        "Ulad Chal\u00edfa",
        "Ul\u00e1d Chlifa",
        "Awl\u0101d Khal\u012bfah"
    ],
    "wof:name":"Awlad Khalifah",
    "wof:placetype":"locality"
},
  "geometry": {"coordinates":[12.25418,31.95326],"type":"Point"}
}