{
  "type": "Feature",
  "properties": {
    "gn:admin1_code":"69",
    "gn:asciiname":"Qaryat al Majaris",
    "gn:country_code":"LY",
    "gn:dem":8,
    "gn:feature_class":"P",
    "gn:feature_code":"PPL",
    "gn:name":"Qaryat al Maj\u0101r\u012bs",
    "gn:population":0,
    "gn:timezone":"Africa/Tripoli",
    "iso:country":"LY",
    "name:ara_x_preferred":[
        "\u0642\u0631\u064a\u0629 \u0627\u0644\u0645\u062c\u0627\u0631\u064a\u0633"
    ],
    "name:und_x_variant":[
        "Qaryat al Maj\u0101r\u012bs"
    ],
    "wof:name":"Qaryat al Majaris",
    "wof:placetype":"locality"
},
  "geometry": {"coordinates":[20.02628,32.01616],"type":"Point"}
}