{
  "type": "Feature",
  "properties": {
    "gn:admin1_code":"63",
    "gn:asciiname":"Bi'r Bin Ghunaymah",
    "gn:country_code":"LY",
    "gn:dem":126,
    "gn:feature_class":"P",
    "gn:feature_code":"PPL",
    "gn:name":"Bi\u2019r Bin Ghunaymah",
    "gn:population":0,
    "gn:timezone":"Africa/Tripoli",
    "iso:country":"LY",
    "name:und_x_variant":[
        "Bi\u2019r Bin Ghunaymah"
    ],
    "wof:name":"Bi'r Bin Ghunaymah",
    "wof:placetype":"locality"
},
  "geometry": {"coordinates":[21.88333,31.18333],"type":"Point"}
}