{
  "type": "Feature",
  "properties": {
    "gn:admin1_code":"81",
    "gn:asciiname":"Bu Ghaylan",
    "gn:country_code":"LY",
    "gn:dem":363,
    "gn:feature_class":"P",
    "gn:feature_code":"PPL",
    "gn:name":"B\u016b Ghayl\u0101n",
    "gn:population":0,
    "gn:timezone":"Africa/Tripoli",
    "iso:country":"LY",
    "name:und_x_variant":[
        "Markaz Bu Ghaylan",
        "Bu Gheilan",
        "B\u016bl\u012bs Ab\u016b Ghayl\u0101h",
        "B\u016b Ghayl\u0101n",
        "\u0628\u0648 \u063a\u064a\u0644\u0627\u0646"
    ],
    "wof:name":"Bu Ghaylan",
    "wof:placetype":"locality"
},
  "geometry": {"coordinates":[13.02909,32.27363],"type":"Point"}
}