{
  "type": "Feature",
  "properties": {
    "gn:admin1_code":"80",
    "gn:asciiname":"Abu Zayyan",
    "gn:country_code":"LY",
    "gn:dem":818,
    "gn:feature_class":"P",
    "gn:feature_code":"PPL",
    "gn:name":"Ab\u016b Zayy\u0101n",
    "gn:population":0,
    "gn:timezone":"Africa/Tripoli",
    "iso:country":"LY",
    "name:und_x_variant":[
        "Bu Zeian",
        "Ab\u016b Ziyy\u0101n",
        "B\u016b Zayy\u0101n",
        "Bu Zai\u00e1n",
        "Ab\u016b Zayy\u0101n"
    ],
    "wof:name":"Abu Zayyan",
    "wof:placetype":"locality"
},
  "geometry": {"coordinates":[12.97861,32.09972],"type":"Point"}
}