{
  "type": "Feature",
  "properties": {
    "gn:admin1_code":"69",
    "gn:asciiname":"Ri'asat Difa` Barqah",
    "gn:country_code":"LY",
    "gn:dem":117,
    "gn:feature_class":"P",
    "gn:feature_code":"PPL",
    "gn:name":"Ri\u2019\u0101sat Dif\u0101\u2018 Barqah",
    "gn:population":0,
    "gn:timezone":"Africa/Tripoli",
    "iso:country":"LY",
    "wof:name":"Ri'asat Difa` Barqah",
    "wof:placetype":"locality"
},
  "geometry": {"coordinates":[20.25,32.06667],"type":"Point"}
}