{
  "type": "Feature",
  "properties": {
    "gn:admin1_code":"69",
    "gn:asciiname":"Sultan",
    "gn:country_code":"LY",
    "gn:dem":11,
    "gn:feature_class":"P",
    "gn:feature_code":"PPL",
    "gn:name":"Sul\u0163\u0101n",
    "gn:population":0,
    "gn:timezone":"Africa/Tripoli",
    "iso:country":"LY",
    "wof:name":"Sultan",
    "wof:placetype":"locality"
},
  "geometry": {"coordinates":[20.22329,31.09396],"type":"Point"}
}