{
  "type": "Feature",
  "properties": {
    "gn:admin1_code":"77",
    "gn:asciiname":"Shatal al Ghabat",
    "gn:country_code":"LY",
    "gn:dem":23,
    "gn:feature_class":"P",
    "gn:feature_code":"PPL",
    "gn:name":"Shatal al Gh\u0101b\u0101t",
    "gn:population":0,
    "gn:timezone":"Africa/Tripoli",
    "iso:country":"LY",
    "wof:name":"Shatal al Ghabat",
    "wof:placetype":"locality"
},
  "geometry": {"coordinates":[13.28583,32.85222],"type":"Point"}
}