{
  "type": "Feature",
  "properties": {
    "gn:admin1_code":"80",
    "gn:asciiname":"Al Kulaybah",
    "gn:country_code":"LY",
    "gn:dem":771,
    "gn:feature_class":"P",
    "gn:feature_code":"PPL",
    "gn:name":"Al Kulaybah",
    "gn:population":0,
    "gn:timezone":"Africa/Tripoli",
    "iso:country":"LY",
    "name:und_x_variant":[
        "El-Culeba",
        "Al Kulaybah"
    ],
    "wof:name":"Al Kulaybah",
    "wof:placetype":"locality"
},
  "geometry": {"coordinates":[13.00389,32.0475],"type":"Point"}
}