{
  "type": "Feature",
  "properties": {
    "gn:admin1_code":"70",
    "gn:asciiname":"Kuhuf Bu Qalbut",
    "gn:country_code":"LY",
    "gn:dem":606,
    "gn:feature_class":"P",
    "gn:feature_code":"PPL",
    "gn:name":"Kuh\u016bf B\u016b Qalb\u016b\u0163",
    "gn:population":0,
    "gn:timezone":"Africa/Tripoli",
    "iso:country":"LY",
    "wof:name":"Kuhuf Bu Qalbut",
    "wof:placetype":"locality"
},
  "geometry": {"coordinates":[22.24884,32.7599],"type":"Point"}
}