{
  "type": "Feature",
  "properties": {
    "gn:admin1_code":"82",
    "gn:asciiname":"Qabilat ash Sha`afiyin",
    "gn:country_code":"LY",
    "gn:dem":351,
    "gn:feature_class":"P",
    "gn:feature_code":"PPL",
    "gn:name":"Qab\u012blat ash Sha\u2018\u0101f\u012by\u012bn",
    "gn:population":0,
    "gn:timezone":"Africa/Tripoli",
    "iso:country":"LY",
    "name:ara_x_preferred":[
        "\u0642\u0628\u064a\u0644\u0629 \u0627\u0644\u0634\u0639\u0627\u0641\u064a\u064a\u0646"
    ],
    "name:und_x_variant":[
        "Ash Shi\u2018\u0101f\u012by\u016bn",
        "Sciaafi\u00edn",
        "Esc-Sciaaf\u00f9n",
        "Qab\u012blat ash Sha\u2018\u0101f\u012by\u012bn",
        "Esc-Sciaafi\u00edn",
        "Qab\u012blat ash Shi\u2018\u0101f\u012by\u012bn"
    ],
    "wof:name":"Qabilat ash Sha`afiyin",
    "wof:placetype":"locality"
},
  "geometry": {"coordinates":[13.88355,32.57125],"type":"Point"}
}