{
  "type": "Feature",
  "properties": {
    "gn:admin1_code":"72",
    "gn:asciiname":"Qaryat al Habarah",
    "gn:country_code":"LY",
    "gn:dem":5,
    "gn:feature_class":"P",
    "gn:feature_code":"PPL",
    "gn:name":"Qaryat al Hab\u0101rah",
    "gn:population":0,
    "gn:timezone":"Africa/Tripoli",
    "iso:country":"LY",
    "name:und_x_variant":[
        "Al Hab\u0101rah",
        "Hab\u00e1ra",
        "El-Hab\u00e1ra",
        "Qaryat al Hab\u0101rah"
    ],
    "wof:name":"Qaryat al Habarah",
    "wof:placetype":"locality"
},
  "geometry": {"coordinates":[15.14877,32.36165],"type":"Point"}
}