{
  "type": "Feature",
  "properties": {
    "gn:admin1_code":"69",
    "gn:asciiname":"Kurkurah",
    "gn:country_code":"LY",
    "gn:dem":1,
    "gn:feature_class":"P",
    "gn:feature_code":"PPL",
    "gn:name":"Kurk\u016brah",
    "gn:population":0,
    "gn:timezone":"Africa/Tripoli",
    "iso:country":"LY",
    "name:und_x_variant":[
        "Carcura",
        "Kark\u016brah",
        "Drepanun",
        "Kurk\u016brah"
    ],
    "wof:name":"Kurkurah",
    "wof:placetype":"locality"
},
  "geometry": {"coordinates":[20.02685,31.4261],"type":"Point"}
}