{
  "type": "Feature",
  "properties": {
    "gn:admin1_code":"82",
    "gn:asciiname":"Qabilat al `Abadilah",
    "gn:country_code":"LY",
    "gn:dem":85,
    "gn:feature_class":"P",
    "gn:feature_code":"PPL",
    "gn:name":"Qab\u012blat al \u2018Ab\u0101d\u012blah",
    "gn:population":0,
    "gn:timezone":"Africa/Tripoli",
    "iso:country":"LY",
    "name:ara_x_preferred":[
        "\u0642\u0628\u064a\u0644\u0629 \u0627\u0644\u0639\u0628\u0627\u062f\u064a\u0644\u0629"
    ],
    "name:und_x_variant":[
        "Qab\u012blat al \u2018Ab\u0101d\u012blah",
        "Qab\u012blat al \u2018Ab\u0101dilah"
    ],
    "wof:name":"Qabilat al `Abadilah",
    "wof:placetype":"locality"
},
  "geometry": {"coordinates":[14.69722,32.28033],"type":"Point"}
}