{
  "type": "Feature",
  "properties": {
    "gn:admin1_code":"80",
    "gn:asciiname":"Qaryat Abu `Ayyad",
    "gn:country_code":"LY",
    "gn:dem":625,
    "gn:feature_class":"P",
    "gn:feature_code":"PPL",
    "gn:name":"Qaryat Ab\u016b \u2018Ayy\u0101d",
    "gn:population":0,
    "gn:timezone":"Africa/Tripoli",
    "iso:country":"LY",
    "name:und_x_variant":[
        "Bu Aiad",
        "Qaryat Ab\u016b \u2018Ayy\u0101d"
    ],
    "wof:name":"Qaryat Abu `Ayyad",
    "wof:placetype":"locality"
},
  "geometry": {"coordinates":[12.97,32.12389],"type":"Point"}
}