{
  "type": "Feature",
  "properties": {
    "gn:admin1_code":"72",
    "gn:asciiname":"Qaryat `Ayn Kurayyim",
    "gn:country_code":"LY",
    "gn:dem":6,
    "gn:feature_class":"P",
    "gn:feature_code":"PPL",
    "gn:name":"Qaryat \u2018Ayn Kurayyim",
    "gn:population":0,
    "gn:timezone":"Africa/Tripoli",
    "iso:country":"LY",
    "wof:name":"Qaryat `Ayn Kurayyim",
    "wof:placetype":"locality"
},
  "geometry": {"coordinates":[15.13787,32.38867],"type":"Point"}
}